maxplotlib/__init__.py
maxplotlib/cli.py
maxplotlib/plot.py
maxplotlib/run.py
maxplotlib/llm/__init__.py
maxplotlib/llm/anthropic_provider.py
maxplotlib/llm/llm_interface.py
maxplotlib/llm/mlx_generation.py
maxplotlib/llm/mlx_provider.py
maxplotlib/llm/openai_provider.py
server/__init__.py
server/server.py
maxplotlib-0.1.9.dist-info/LICENSE
maxplotlib-0.1.9.dist-info/METADATA
maxplotlib-0.1.9.dist-info/WHEEL
maxplotlib-0.1.9.dist-info/entry_points.txt
maxplotlib-0.1.9.dist-info/top_level.txt
maxplotlib-0.1.9.dist-info/RECORD
