Metadata-Version: 2.1
Name: maxplotlib
Version: 0.1.9
Summary: Autoviz API by Max Cembalest
Home-page: http://github.com/mcembalest/maxplotlib
Author: Max Cembalest
Author-email: macembalest@gmail.com
License: LICENSE
Classifier: Development Status :: 3 - Alpha
Classifier: Intended Audience :: Developers
Classifier: Topic :: Software Development
Classifier: License :: OSI Approved :: Apache Software License
Classifier: Programming Language :: Python :: 3
Classifier: Programming Language :: Python :: 3.8
Classifier: Programming Language :: Python :: 3.9
Classifier: Programming Language :: Python :: 3.10
Classifier: Programming Language :: Python :: 3.11
Classifier: Programming Language :: Python :: 3.12
Requires-Python: >=3.8
License-File: LICENSE
Provides-Extra: server
Requires-Dist: matplotlib ; extra == 'server'
Requires-Dist: mlx-lm ; extra == 'server'
Requires-Dist: numpy ; extra == 'server'
Requires-Dist: pillow ; extra == 'server'
Requires-Dist: plotly ; extra == 'server'
Requires-Dist: torch ; extra == 'server'
